{"paijiuCardGroupData": {"24,31": {"id": "24,31", "name": "mixfive"}, "17,32": {"id": "17,32", "name": "shortthree"}, "7,29": {"id": "7,29", "name": "sumnine"}, "3,32": {"id": "3,32", "name": "fieldfive"}, "9,9": {"id": "9,9", "name": "doublelongten"}, "13,27": {"id": "13,27", "name": "longone"}, "7,9": {"id": "7,9", "name": "sumfour"}, "19,21": {"id": "19,21", "name": "shortthree"}, "13,11": {"id": "13,11", "name": "zero"}, "24,13": {"id": "24,13", "name": "longthree"}, "26,30": {"id": "26,30", "name": "mixthree"}, "13,26": {"id": "13,26", "name": "longtwo"}, "15,17": {"id": "15,17", "name": "shortone"}, "1,3": {"id": "1,3", "name": "skyfour"}, "1,17": {"id": "1,17", "name": "skytwo"}, "24,25": {"id": "24,25", "name": "mixseven"}, "25,21": {"id": "25,21", "name": "shortfour"}, "15,27": {"id": "15,27", "name": "shorteight"}, "5,13": {"id": "5,13", "name": "peopletwo"}, "26,19": {"id": "26,19", "name": "shortfive"}, "11,27": {"id": "11,27", "name": "longthree"}, "3,25": {"id": "3,25", "name": "fieldstaff"}, "25,15": {"id": "25,15", "name": "shortnine"}, "1,26": {"id": "1,26", "name": "skystaff"}, "17,26": {"id": "17,26", "name": "shorteight"}, "3,30": {"id": "3,30", "name": "fieldseven"}, "9,28": {"id": "9,28", "name": "longseven"}, "24,27": {"id": "24,27", "name": "mixsix"}, "28,29": {"id": "28,29", "name": "mixtwo"}, "9,31": {"id": "9,31", "name": "longsix"}, "9,27": {"id": "9,27", "name": "longseven"}, "11,9": {"id": "11,9", "name": "longsix"}, "1,27": {"id": "1,27", "name": "skynine"}, "27,28": {"id": "27,28", "name": "doublepointseven"}, "23,24": {"id": "23,24", "name": "doublepointnine"}, "11,17": {"id": "11,17", "name": "longsix"}, "29,30": {"id": "29,30", "name": "doublepointfive"}, "25,30": {"id": "25,30", "name": "mixthree"}, "27,21": {"id": "27,21", "name": "shortthree"}, "31,32": {"id": "31,32", "name": "king"}, "27,31": {"id": "27,31", "name": "mixthree"}, "5,21": {"id": "5,21", "name": "peoplefour"}, "9,24": {"id": "9,24", "name": "longnine"}, "11,31": {"id": "11,31", "name": "longtwo"}, "30,19": {"id": "30,19", "name": "shorttwo"}, "19,19": {"id": "19,19", "name": "doubleshortseven"}, "1,24": {"id": "1,24", "name": "skynineking"}, "19,28": {"id": "19,28", "name": "shortfour"}, "24,26": {"id": "24,26", "name": "mixseven"}, "1,7": {"id": "1,7", "name": "skysix"}, "5,11": {"id": "5,11", "name": "peoplefour"}, "28,21": {"id": "28,21", "name": "shortthree"}, "17,31": {"id": "17,31", "name": "shortsix"}, "7,17": {"id": "7,17", "name": "sumfour"}, "1,19": {"id": "1,19", "name": "skynine"}, "23,27": {"id": "23,27", "name": "mixsix"}, "23,31": {"id": "23,31", "name": "mixfive"}, "1,11": {"id": "1,11", "name": "skyeight"}, "1,15": {"id": "1,15", "name": "skythree"}, "26,21": {"id": "26,21", "name": "shortfour"}, "11,21": {"id": "11,21", "name": "longtwo"}, "3,24": {"id": "3,24", "name": "fieldone"}, "9,19": {"id": "9,19", "name": "longseven"}, "32,21": {"id": "32,21", "name": "shortnine"}, "24,28": {"id": "24,28", "name": "mixsix"}, "30,31": {"id": "30,31", "name": "mixone"}, "3,21": {"id": "3,21", "name": "fieldeight"}, "13,25": {"id": "13,25", "name": "longtwo"}, "29,19": {"id": "29,19", "name": "shorttwo"}, "13,32": {"id": "13,32", "name": "longseven"}, "9,15": {"id": "9,15", "name": "longone"}, "15,21": {"id": "15,21", "name": "shortseven"}, "21,31": {"id": "21,31", "name": "shorttwo"}, "24,19": {"id": "24,19", "name": "shortsix"}, "13,28": {"id": "13,28", "name": "longone"}, "3,15": {"id": "3,15", "name": "fieldthree"}, "28,30": {"id": "28,30", "name": "mixtwo"}, "11,23": {"id": "11,23", "name": "longfive"}, "28,32": {"id": "28,32", "name": "zero"}, "26,29": {"id": "26,29", "name": "mixthree"}, "23,29": {"id": "23,29", "name": "mixfour"}, "9,13": {"id": "9,13", "name": "longfour"}, "7,21": {"id": "7,21", "name": "zero"}, "1,21": {"id": "1,21", "name": "skyeight"}, "7,31": {"id": "7,31", "name": "zero"}, "3,7": {"id": "3,7", "name": "fieldsix"}, "15,32": {"id": "15,32", "name": "shortfour"}, "11,26": {"id": "11,26", "name": "longfour"}, "5,15": {"id": "5,15", "name": "peoplenine"}, "25,19": {"id": "25,19", "name": "shortfive"}, "17,21": {"id": "17,21", "name": "shortsix"}, "21,21": {"id": "21,21", "name": "doubleshortsix"}, "3,29": {"id": "3,29", "name": "fieldseven"}, "17,13": {"id": "17,13", "name": "longfour"}, "5,7": {"id": "5,7", "name": "peopletwo"}, "25,32": {"id": "25,32", "name": "mixone"}, "19,31": {"id": "19,31", "name": "shortthree"}, "25,31": {"id": "25,31", "name": "mixfour"}, "1,13": {"id": "1,13", "name": "skysix"}, "15,23": {"id": "15,23", "name": "ghost"}, "3,23": {"id": "3,23", "name": "fieldone"}, "23,19": {"id": "23,19", "name": "shortsix"}, "24,32": {"id": "24,32", "name": "mixtwo"}, "9,17": {"id": "9,17", "name": "zero"}, "13,13": {"id": "13,13", "name": "doublelongfour"}, "7,24": {"id": "7,24", "name": "sumthree"}, "7,11": {"id": "7,11", "name": "zero"}, "24,30": {"id": "24,30", "name": "mixfour"}, "5,27": {"id": "5,27", "name": "peoplefive"}, "3,5": {"id": "3,5", "name": "fieldstaff"}, "27,29": {"id": "27,29", "name": "mixtwo"}, "7,26": {"id": "7,26", "name": "sumtwo"}, "25,27": {"id": "25,27", "name": "mixfive"}, "11,29": {"id": "11,29", "name": "longone"}, "23,26": {"id": "23,26", "name": "mixseven"}, "17,25": {"id": "17,25", "name": "shorteight"}, "5,25": {"id": "5,25", "name": "peoplesix"}, "9,21": {"id": "9,21", "name": "longsix"}, "1,25": {"id": "1,25", "name": "skystaff"}, "23,21": {"id": "23,21", "name": "shortfive"}, "5,9": {"id": "5,9", "name": "peopleeight"}, "7,28": {"id": "7,28", "name": "sumone"}, "7,25": {"id": "7,25", "name": "sumtwo"}, "11,11": {"id": "11,11", "name": "doublelongsix"}, "7,15": {"id": "7,15", "name": "sumfive"}, "7,7": {"id": "7,7", "name": "doublesum"}, "7,19": {"id": "7,19", "name": "sumone"}, "1,31": {"id": "1,31", "name": "skyeight"}, "25,29": {"id": "25,29", "name": "mixthree"}, "23,25": {"id": "23,25", "name": "mixseven"}, "19,27": {"id": "19,27", "name": "shortfour"}, "1,23": {"id": "1,23", "name": "skynineking"}, "19,32": {"id": "19,32", "name": "zero"}, "1,29": {"id": "1,29", "name": "skyseven"}, "3,13": {"id": "3,13", "name": "fieldsix"}, "26,28": {"id": "26,28", "name": "mixfive"}, "23,32": {"id": "23,32", "name": "mixtwo"}, "3,3": {"id": "3,3", "name": "doublefield"}, "9,30": {"id": "9,30", "name": "longfive"}, "29,31": {"id": "29,31", "name": "mixone"}, "1,9": {"id": "1,9", "name": "skytwo"}, "7,13": {"id": "7,13", "name": "sumeight"}, "5,23": {"id": "5,23", "name": "peopleseven"}, "13,31": {"id": "13,31", "name": "zero"}, "15,31": {"id": "15,31", "name": "shortseven"}, "9,26": {"id": "9,26", "name": "longeight"}, "9,23": {"id": "9,23", "name": "longnine"}, "21,30": {"id": "21,30", "name": "shortone"}, "24,17": {"id": "24,17", "name": "shortnine"}, "15,29": {"id": "15,29", "name": "shortsix"}, "15,24": {"id": "15,24", "name": "ghost"}, "11,19": {"id": "11,19", "name": "longthree"}, "1,32": {"id": "1,32", "name": "skyfive"}, "5,17": {"id": "5,17", "name": "peopleeight"}, "28,31": {"id": "28,31", "name": "mixthree"}, "7,30": {"id": "7,30", "name": "sumnine"}, "25,28": {"id": "25,28", "name": "mixfive"}, "15,13": {"id": "15,13", "name": "longfive"}, "32,29": {"id": "32,29", "name": "mixeight"}, "5,32": {"id": "5,32", "name": "peopleone"}, "13,29": {"id": "13,29", "name": "longnine"}, "13,21": {"id": "13,21", "name": "zero"}, "25,26": {"id": "25,26", "name": "doublepointeight"}, "15,15": {"id": "15,15", "name": "doubleshorteleven"}, "26,27": {"id": "26,27", "name": "mixfive"}, "3,11": {"id": "3,11", "name": "fieldeight"}, "3,17": {"id": "3,17", "name": "fieldtwo"}, "17,27": {"id": "17,27", "name": "shortseven"}, "24,29": {"id": "24,29", "name": "mixfour"}, "9,32": {"id": "9,32", "name": "longthree"}, "1,1": {"id": "1,1", "name": "doublesky"}, "7,23": {"id": "7,23", "name": "sumthree"}, "15,28": {"id": "15,28", "name": "shorteight"}, "5,26": {"id": "5,26", "name": "peoplesix"}, "1,28": {"id": "1,28", "name": "skynine"}, "11,24": {"id": "11,24", "name": "longfive"}, "32,30": {"id": "32,30", "name": "mixeight"}, "3,26": {"id": "3,26", "name": "fieldstaff"}, "13,19": {"id": "13,19", "name": "longone"}, "27,32": {"id": "27,32", "name": "zero"}, "26,15": {"id": "26,15", "name": "shortnine"}, "5,31": {"id": "5,31", "name": "peoplefour"}, "5,28": {"id": "5,28", "name": "peoplefive"}, "23,30": {"id": "23,30", "name": "mixfour"}, "3,19": {"id": "3,19", "name": "fieldnine"}, "5,19": {"id": "5,19", "name": "peoplefive"}, "3,28": {"id": "3,28", "name": "fieldnine"}, "23,28": {"id": "23,28", "name": "mixsix"}, "26,32": {"id": "26,32", "name": "mixone"}, "3,9": {"id": "3,9", "name": "fieldtwo"}, "11,28": {"id": "11,28", "name": "longthree"}, "15,30": {"id": "15,30", "name": "shortsix"}, "11,32": {"id": "11,32", "name": "longnine"}, "21,29": {"id": "21,29", "name": "shortone"}, "26,31": {"id": "26,31", "name": "mixfour"}, "3,31": {"id": "3,31", "name": "fieldeight"}, "24,21": {"id": "24,21", "name": "shortfive"}, "13,30": {"id": "13,30", "name": "longnine"}, "3,27": {"id": "3,27", "name": "fieldnine"}, "5,29": {"id": "5,29", "name": "peoplethree"}, "9,29": {"id": "9,29", "name": "longfive"}, "15,11": {"id": "15,11", "name": "longseven"}, "17,30": {"id": "17,30", "name": "shortfive"}, "17,29": {"id": "17,29", "name": "shortfive"}, "7,27": {"id": "7,27", "name": "sumone"}, "15,19": {"id": "15,19", "name": "shorteight"}, "11,30": {"id": "11,30", "name": "longone"}, "5,30": {"id": "5,30", "name": "peoplethree"}, "17,19": {"id": "17,19", "name": "shortseven"}, "9,25": {"id": "9,25", "name": "longeight"}, "5,5": {"id": "5,5", "name": "doublepeople"}, "23,17": {"id": "23,17", "name": "shortnine"}, "7,32": {"id": "7,32", "name": "sumseven"}, "1,30": {"id": "1,30", "name": "skyseven"}, "17,17": {"id": "17,17", "name": "doubleshortten"}, "1,5": {"id": "1,5", "name": "skystaff"}, "27,30": {"id": "27,30", "name": "mixtwo"}, "5,24": {"id": "5,24", "name": "peopleseven"}, "23,13": {"id": "23,13", "name": "longthree"}, "17,28": {"id": "17,28", "name": "shortseven"}, "11,25": {"id": "11,25", "name": "longfour"}}, "paijiuCardGroupScoreData": {"shortfour": {"id": "shortfour", "score": 22}, "doublelongsix": {"id": "doublelongsix", "score": 120}, "shorttwo": {"id": "shorttwo", "score": 8}, "fieldsix": {"id": "fieldsix", "score": 38}, "longtwo": {"id": "longtwo", "score": 9}, "shortseven": {"id": "shortseven", "score": 41}, "mixfive": {"id": "mixfive", "score": 27}, "mixone": {"id": "mixone", "score": 1}, "mixfour": {"id": "mixfour", "score": 21}, "doublepointseven": {"id": "doublepointseven", "score": 80}, "longsix": {"id": "longsix", "score": 36}, "peoplefive": {"id": "peoplefive", "score": 31}, "sumeight": {"id": "sumeight", "score": 50}, "doubleshortsix": {"id": "doubleshortsix", "score": 110}, "fieldone": {"id": "fieldone", "score": 6}, "fieldseven": {"id": "fieldseven", "score": 45}, "doublesum": {"id": "doublesum", "score": 130}, "skythree": {"id": "skythree", "score": 20}, "peopleone": {"id": "peopleone", "score": 5}, "longfive": {"id": "longfive", "score": 29}, "doublepointnine": {"id": "doublepointnine", "score": 100}, "skyfive": {"id": "skyfive", "score": 33}, "shortthree": {"id": "shortthree", "score": 15}, "sumthree": {"id": "sumthree", "score": 17}, "skytwo": {"id": "skytwo", "score": 13}, "shortone": {"id": "shortone", "score": 2}, "skyeight": {"id": "skyeight", "score": 53}, "mixeight": {"id": "mixeight", "score": 47}, "shorteight": {"id": "shorteight", "score": 48}, "zero": {"id": "zero"}, "doublepointfive": {"id": "doublepointfive", "score": 70}, "longnine": {"id": "longnine", "score": 55}, "peoplenine": {"id": "peoplenine", "score": 57}, "skysix": {"id": "skysix", "score": 39}, "fieldfive": {"id": "fieldfive", "score": 32}, "skystaff": {"id": "skystaff", "score": 61}, "peoplesix": {"id": "peoplesix", "score": 37}, "mixseven": {"id": "mixseven", "score": 40}, "peopletwo": {"id": "peopletwo", "score": 11}, "peoplethree": {"id": "peoplethree", "score": 18}, "longone": {"id": "longone", "score": 3}, "sumone": {"id": "sumone", "score": 4}, "mixthree": {"id": "mixthree", "score": 14}, "fieldthree": {"id": "fieldthree", "score": 19}, "longthree": {"id": "longthree", "score": 16}, "doublelongfour": {"id": "doublelongfour", "score": 120}, "sumfive": {"id": "sumfive", "score": 30}, "ghost": {"id": "ghost", "score": 190}, "shortfive": {"id": "shortfive", "score": 28}, "longfour": {"id": "longfour", "score": 23}, "peoplefour": {"id": "peoplefour", "score": 25}, "longseven": {"id": "longseven", "score": 42}, "king": {"id": "king", "score": 180}, "sumseven": {"id": "sumseven", "score": 43}, "fieldstaff": {"id": "fieldstaff", "score": 60}, "doubleshortseven": {"id": "doubleshortseven", "score": 110}, "doubleshortten": {"id": "doubleshortten", "score": 110}, "doubleshorteleven": {"id": "doubleshorteleven", "score": 110}, "shortsix": {"id": "shortsix", "score": 35}, "doublepeople": {"id": "doublepeople", "score": 140}, "sumtwo": {"id": "sumtwo", "score": 10}, "fieldnine": {"id": "fieldnine", "score": 58}, "skyfour": {"id": "skyfour", "score": 26}, "mixtwo": {"id": "mixtwo", "score": 7}, "peopleeight": {"id": "peopleeight", "score": 51}, "skyseven": {"id": "skyseven", "score": 46}, "doublepointeight": {"id": "doublepointeight", "score": 90}, "sumfour": {"id": "sumfour", "score": 24}, "doublesky": {"id": "doublesky", "score": 160}, "doublelongten": {"id": "doublelongten", "score": 120}, "skynine": {"id": "skynine", "score": 59}, "longeight": {"id": "longeight", "score": 49}, "fieldeight": {"id": "fieldeight", "score": 52}, "mixsix": {"id": "mixsix", "score": 34}, "peopleseven": {"id": "peopleseven", "score": 44}, "doublefield": {"id": "doublefield", "score": 150}, "skynineking": {"id": "skynineking", "score": 170}, "fieldtwo": {"id": "fieldtwo", "score": 12}, "shortnine": {"id": "shortnine", "score": 54}, "sumnine": {"id": "sumnine", "score": 56}}, "testData": {"1": {"id": 1, "testMapDouble": {"1": 5.0}, "weapon": {"1": "10", "2": "20"}, "name": "zjm", "testLong": "1", "exp": [3, 4, 10], "testDouble": 1.1, "testListDouble": [1.1, 2.2, 3.3]}, "2": {"id": 2, "testMapDouble": {"4": 6.0}, "weapon": {"1": "30", "2": "50"}, "name": "zjm", "testLong": "2", "exp": [1, 2], "age": 1, "testDouble": 10.23, "testListDouble": [1.2]}}, "roomData": {"0": {"money": {"10": 1, "20": 2}, "eachMoney": {"1": 10, "2": 20}}, "1": {"id": 1, "money": {"10": 1, "20": 2}, "eachMoney": {"1": 30, "2": 50}}, "2": {"id": 2, "money": {"9": 20, "2": 30, "18": 45, "30": 60}, "isAddGold": 1, "eachMoney": {"9": 10, "2": 10, "18": 15, "30": 20}}, "3": {"id": 3, "money": {"9": 25, "2": 30, "18": 45, "30": 60}, "isAddGold": 1, "eachMoney": {"9": 10, "2": 10, "18": 15, "30": 20}}, "4": {"id": 4, "money": {"9": 30, "2": 30, "18": 45, "30": 60}, "isAddGold": 1, "eachMoney": {"9": 10, "2": 10, "18": 15, "30": 20}}, "5": {"id": 5, "money": {"9": 30, "2": 30, "18": 45, "30": 60}, "isAddGold": 1, "eachMoney": {"9": 10, "2": 10, "18": 15, "30": 20}}, "6": {"id": 6, "money": {"20": 3, "2": 30, "12": 2, "6": 1}, "eachMoney": {"20": 3, "2": 30, "12": 2, "6": 1}}, "10": {"id": 10, "money": {"24": 2, "2": 1, "12": 1}, "eachMoney": {"24": 2, "2": 1, "12": 1}}, "11": {"id": 11, "money": {"0": 2}, "eachMoney": {"0": 2}}, "12": {"id": 12, "money": {"24": 2, "2": 1, "12": 1}, "eachMoney": {"24": 2, "2": 1, "12": 1}}, "13": {"id": 13, "money": {"0": 2}, "eachMoney": {"0": 2}}, "30": {"id": 30, "money": {"20": 3, "12": 2, "6": 1}, "eachMoney": {"20": 3, "12": 2, "6": 1}}}, "paijiuCardData": {"1": {"id": 1, "card": 1}, "2": {"id": 2, "card": 1}, "3": {"id": 3, "card": 3}, "4": {"id": 4, "card": 3}, "5": {"id": 5, "card": 5}, "6": {"id": 6, "card": 5}, "7": {"id": 7, "card": 7}, "8": {"id": 8, "card": 7}, "9": {"id": 9, "card": 9}, "10": {"id": 10, "card": 9}, "11": {"id": 11, "card": 11}, "12": {"id": 12, "card": 11}, "13": {"id": 13, "card": 13}, "14": {"id": 14, "card": 13}, "15": {"id": 15, "card": 15}, "16": {"id": 16, "card": 15}, "17": {"id": 17, "card": 17}, "18": {"id": 18, "card": 17}, "19": {"id": 19, "card": 19}, "20": {"id": 20, "card": 19}, "21": {"id": 21, "card": 21}, "22": {"id": 22, "card": 21}, "23": {"id": 23, "card": 23}, "24": {"id": 24, "card": 24}, "25": {"id": 25, "card": 25}, "26": {"id": 26, "card": 26}, "27": {"id": 27, "card": 27}, "28": {"id": 28, "card": 28}, "29": {"id": 29, "card": 29}, "30": {"id": 30, "card": 30}, "31": {"id": 31, "card": 31}, "32": {"id": 32, "card": 32}}}